{"data": [{
  "all_phases": [
    {
      "additional_text": null,
      "display_name": "General availability",
      "name": "General availability",
      "ptype": "normal",
      "tooltip": null
    },
    {
      "additional_text": null,
      "display_name": "Full support ends",
      "name": "Full support",
      "ptype": "normal",
      "tooltip": null
    },
    {
      "additional_text": null,
      "display_name": "Maintenance support ends",
      "name": "Maintenance support",
      "ptype": "normal",
      "tooltip": null
    }
  ],
  "footnote": "<p><strong>NOTE:</strong> Only the latest update of 2.4.x version of the Red Hat JBoss Core Services HTTP server is maintained.</p>\n",
  "former_names": [],
  "is_layered_product": false,
  "is_operator": false,
  "link": "https://access.redhat.com/support/policy/updates/jboss_notes/",
  "name": "Apache HTTP Server",
  "package": null,
  "release_cadence": null,
  "show_final_minor_release": false,
  "show_last_minor_release": false,
  "show_openshift_compatibility": false,
  "uuid": "6e896843-d9b7-4cd8-820d-546c653aac77",
  "versions": [
    {
      "additional_text": "",
      "extra_dependences": [],
      "extra_header_value": null,
      "final_minor_release": null,
      "last_minor_release": null,
      "name": "2.4.x",
      "openshift_compatibility": null,
      "phases": [
        {
          "additional_text": "",
          "date": "2016-05-01T00:00:00.000Z",
          "date_format": "date",
          "name": "General availability"
        },
        {
          "additional_text": "",
          "date": "2028-07-31T00:00:00.000Z",
          "date_format": "date",
          "name": "Full support"
        },
        {
          "additional_text": "",
          "date": "2029-07-31T00:00:00.000Z",
          "date_format": "date",
          "name": "Maintenance support"
        }
      ],
      "tier": "N/A",
      "type": "Full Support"
    }
  ]
}]}