{"data": [{
  "all_phases": [
    {
      "additional_text": null,
      "display_name": "General availability",
      "name": "General availability",
      "ptype": "normal",
      "tooltip": null
    },
    {
      "additional_text": null,
      "display_name": "Full support ends",
      "name": "Full support",
      "ptype": "normal",
      "tooltip": null
    },
    {
      "additional_text": null,
      "display_name": "Maintenance support ends",
      "name": "Maintenance support",
      "ptype": "normal",
      "tooltip": null
    },
    {
      "additional_text": null,
      "display_name": "Extended life cycle support (ELS) 1 ends",
      "name": "Extended life cycle support (ELS) 1",
      "ptype": "extended",
      "tooltip": "The Extended Life Cycle Phase (ELP) is the post-retirement time period. We require that customers running Red Hat Enterprise Linux products beyond their retirement continue to have active subscriptions which ensures that they continue receiving access to all previously released content, documentation, and knowledge base articles as well as receive limited technical support. As there are no bug fixes, security fixes, hardware enablement, or root cause analysis available during the Extended Life Phase, customers may choose to purchase the Extended Life Cycle Support Add-On during the Extended Life Phase, which will provide them with critical impact security fixes and selected urgent priority bug fixes."
    }
  ],
  "extra_header": "Tier",
  "footnote": "<p><strong>NOTE:</strong> Please see article <a href=\"https://access.redhat.com/support/policy/updates/service-interconnect\">&quot;Red Hat Service Interconnect&quot;</a> for detailed information about the Red Hat Service Interconnect life cycle.</p>\n",
  "former_names": [],
  "is_layered_product": true,
  "is_operator": true,
  "link": "https://access.redhat.com/support/policy/updates/jboss_notes/",
  "name": "Red Hat Service Interconnect",
  "package": "skupper-operator",
  "product_extra_headers": [],
  "release_cadence": "Not Specified",
  "show_final_minor_release": false,
  "show_last_minor_release": false,
  "show_openshift_compatibility": true,
  "uuid": "eb13f5fd-57cc-4345-b315-8afce85f9033",
  "versions": [
    {
      "additional_text": "",
      "extra_dependences": [],
      "extra_header_value": "N/A",
      "final_minor_release": null,
      "last_minor_release": null,
      "name": "1.5.x",
      "openshift_compatibility": "",
      "phases": [
        {
          "additional_text": "",
          "date": "2023-11-02T00:00:00.000Z",
          "date_format": "date",
          "name": "General availability"
        },
        {
          "additional_text": "",
          "date": "2024-11-02T00:00:00.000Z",
          "date_format": "date",
          "name": "Full support"
        },
        {
          "additional_text": "",
          "date": "",
          "date_format": "string",
          "name": "Maintenance support"
        },
        {
          "date": "N/A",
          "date_format": "string",
          "name": "Extended life cycle support (ELS) 1"
        }
      ],
      "tier": "N/A",
      "type": "Full Support"
    },
    {
      "additional_text": "",
      "extra_dependences": [],
      "extra_header_value": "N/A",
      "final_minor_release": null,
      "last_minor_release": null,
      "name": "1.4.x",
      "openshift_compatibility": "",
      "phases": [
        {
          "additional_text": "",
          "date": "2023-07-11T00:00:00.000Z",
          "date_format": "date",
          "name": "General availability"
        },
        {
          "additional_text": "",
          "date": "2024-07-11T00:00:00.000Z",
          "date_format": "date",
          "name": "Full support"
        },
        {
          "additional_text": "",
          "date": "2025-07-11T00:00:00.000Z",
          "date_format": "date",
          "name": "Maintenance support"
        },
        {
          "date": "N/A",
          "date_format": "string",
          "name": "Extended life cycle support (ELS) 1"
        }
      ],
      "tier": "N/A",
      "type": "Maintenance Support"
    }
  ]
}]}